gramup/__init__.py
gramup/__main__.py
gramup/backup.py
gramup/constants.py
gramup/help.py
gramup/login.py
gramup/restore.py
gramup/search.py
gramup/settings.py
gramup/utils.py
gramup-2.1.0.dist-info/LICENSE
gramup-2.1.0.dist-info/METADATA
gramup-2.1.0.dist-info/WHEEL
gramup-2.1.0.dist-info/entry_points.txt
gramup-2.1.0.dist-info/top_level.txt
gramup-2.1.0.dist-info/RECORD
