Metadata-Version: 2.1
Name: gramup
Version: 2.1.0
Summary: A utility to use Telegram as a backup solution.
Home-page: https://github.com/rohittp0/GramUp
Author: Rohit T P
Author-email: tprohit9@gmail.com
License: UNKNOWN
Platform: UNKNOWN
Classifier: Programming Language :: Python :: 3
Classifier: License :: OSI Approved :: GNU Affero General Public License v3
Classifier: Operating System :: Unix
Requires-Python: >=3.8
Requires-Dist: blessings (==1.7)
Requires-Dist: curtsies (==0.3.10)
Requires-Dist: cwcwidth (==0.1.5)
Requires-Dist: enquiries (==0.1.0)
Requires-Dist: python-telegram (==0.14.0)
Requires-Dist: six (==1.16.0)
Requires-Dist: speedtest-cli (==2.1.3)
